{
  "portfolio": {
    "address": "0x5d0e4a3d6ca907fe5b51131e2aee726b84b86e4d",
    "totalValue": "$8,609",
    "walletLifetime": "371 days",
    "tokens": [
      {
        "symbol": "PEPE",
        "chain": "eth",
        "price": "$0.0₅4679",
        "amount": "1,824,313,720.1712",
        "usdValue": "$8,535.44"
      },
      {
        "symbol": "ETH",
        "chain": "eth",
        "price": "$3,107.7100",
        "amount": "0.0227",
        "usdValue": "$70.64"
      },
      {
        "symbol": "VIRGEN",
        "chain": "base",
        "price": "$0.0004",
        "amount": "7,275.2700",
        "usdValue": "$2.86"
      },
      {
        "symbol": "731",
        "chain": "xlayer",
        "price": "$0.00004826",
        "amount": "731.0000",
        "usdValue": "$0.04"
      },
      {
        "symbol": "MON",
        "chain": "monad",
        "price": "$0.0276",
        "amount": "1.0000",
        "usdValue": "$0.03"
      },
      {
        "symbol": "BASED",
        "chain": "base",
        "price": "$0.00001001",
        "amount": "350.0000",
        "usdValue": ""
      },
      {
        "symbol": "MOODENG",
        "chain": "eth",
        "price": "$0.00001502",
        "amount": "30.0000",
        "usdValue": ""
      },
      {
        "symbol": "FOFAR",
        "chain": "base",
        "price": "$0.0₅7854",
        "amount": "1.5000",
        "usdValue": ""
      },
      {
        "symbol": "PEPEBET",
        "chain": "eth",
        "price": "$0.0000",
        "amount": "31.2357",
        "usdValue": "$0.00"
      },
      {
        "symbol": "META",
        "chain": "base",
        "price": "$0.0000",
        "amount": "10.2765",
        "usdValue": "$0.00"
      }
    ],
    "positions": []
  },
  "analysis": {
    "address": "0x5d0e4a3d6ca907fe5b51131e2aee726b84b86e4d",
    "topProtocols": [
      {
        "name": "Aave V3",
        "volume": "$177K"
      },
      {
        "name": "0x8d8c…518b",
        "volume": "$53K"
      },
      {
        "name": "0x7e6c…1d48",
        "volume": "$36K"
      },
      {
        "name": "CoW Swap",
        "volume": "$35K"
      },
      {
        "name": "Uniswap V4",
        "volume": "$13K"
      },
      {
        "name": "0x10e7…98a7",
        "volume": "$9K"
      },
      {
        "name": "0xeff6…a167",
        "volume": "$6K"
      },
      {
        "name": "0x9052…3714",
        "volume": "$484"
      },
      {
        "name": "disperse",
        "volume": "$77"
      },
      {
        "name": "0x46c1…7838",
        "volume": "$47"
      },
      {
        "name": "0x8b13…dd82",
        "volume": "$3"
      },
      {
        "name": "0x4b85…c0d6",
        "volume": "$3"
      },
      {
        "name": "0x72fe…cd58",
        "volume": "$unknown"
      },
      {
        "name": "0xb612…c26d",
        "volume": "$unknown"
      },
      {
        "name": "0xfe17…f2b0",
        "volume": "$unknown"
      },
      {
        "name": "0x647c…c209",
        "volume": "$unknown"
      },
      {
        "name": "0xdf74…32bb",
        "volume": "$unknown"
      }
    ],
    "topTokens": [
      {
        "name": "ETH",
        "volume": "$172K"
      },
      {
        "name": "LINK",
        "volume": "$71K"
      },
      {
        "name": "USDC",
        "volume": "$40K"
      },
      {
        "name": "AAVE",
        "volume": "$37K"
      },
      {
        "name": "PEPE",
        "volume": "$27K"
      },
      {
        "name": "ENS",
        "volume": "$15K"
      },
      {
        "name": "VIRGEN",
        "volume": "$77M"
      }
    ]
  },
  "scrapedAt": "2025-12-09T02:44:42.738Z",
  "source": "aave_mainnet",
  "vaultBalance": 16.332911856636812,
  "vaultPct": 0.003036893159401996
}