{
  "portfolio": {
    "address": "0x6cb1f3e253929d3e821a4213dea405524bedc1f1",
    "totalValue": "$513",
    "walletLifetime": "1213 days",
    "tokens": [
      {
        "symbol": "ETH",
        "chain": "eth",
        "price": "$3,121.2700",
        "amount": "0.1643",
        "usdValue": "$512.77"
      }
    ],
    "positions": []
  },
  "analysis": {
    "address": "0x6cb1f3e253929d3e821a4213dea405524bedc1f1",
    "topProtocols": [
      {
        "name": "Aave V3",
        "volume": "$105K"
      },
      {
        "name": "0x",
        "volume": "$48K"
      },
      {
        "name": "SushiSwap V3",
        "volume": "$30K"
      },
      {
        "name": "Coinbase",
        "volume": "$23K"
      },
      {
        "name": "1inch",
        "volume": "$22K"
      },
      {
        "name": "Uniswap V3",
        "volume": "$7K"
      },
      {
        "name": "Index Coop",
        "volume": "$2K"
      },
      {
        "name": "0x0000…89be",
        "volume": "$2K"
      },
      {
        "name": "Wrapped Ether",
        "volume": "$2K"
      },
      {
        "name": "Bungee",
        "volume": "$1K"
      },
      {
        "name": "Across V2",
        "volume": "$1K"
      },
      {
        "name": "0xc3c9…550f",
        "volume": "$unknown"
      }
    ],
    "topTokens": [
      {
        "name": "ETH",
        "volume": "$112K"
      },
      {
        "name": "WBTC",
        "volume": "$85K"
      },
      {
        "name": "USDC",
        "volume": "$76K"
      },
      {
        "name": "UNI",
        "volume": "$5K"
      },
      {
        "name": "AAVE",
        "volume": "$3K"
      },
      {
        "name": "WETH",
        "volume": "$3K"
      },
      {
        "name": "SHIB",
        "volume": "$2K"
      },
      {
        "name": "KEIGEN",
        "volume": "$462"
      },
      {
        "name": "BOOMER",
        "volume": "$unknown"
      }
    ]
  },
  "scrapedAt": "2025-12-09T01:27:37.441Z",
  "source": "aave_mainnet",
  "vaultBalance": 0.15000000000000002,
  "vaultPct": 0.000027890554844646094
}