{
  "portfolio": {
    "address": "0x7398944e67dbe99ada77818f120282ab9fe4311c",
    "totalValue": "$206",
    "walletLifetime": "1556 days",
    "tokens": [
      {
        "symbol": "ETH",
        "chain": "eth",
        "price": "$3,108.9000",
        "amount": "0.0591",
        "usdValue": "$183.86"
      },
      {
        "symbol": "POL",
        "chain": "matic",
        "price": "$0.1240",
        "amount": "177.0427",
        "usdValue": "$21.95"
      },
      {
        "symbol": "MegaDoge",
        "chain": "matic",
        "price": "$0.00009108",
        "amount": "1,000.0000",
        "usdValue": "$0.09"
      },
      {
        "symbol": "MON",
        "chain": "monad",
        "price": "$0.0280",
        "amount": "1.0000",
        "usdValue": "$0.03"
      },
      {
        "symbol": "BASED",
        "chain": "base",
        "price": "$0.0₅9821",
        "amount": "375.0000",
        "usdValue": ""
      },
      {
        "symbol": "CHZ",
        "chain": "eth",
        "price": "$0.0316",
        "amount": "0.00003165",
        "usdValue": ""
      },
      {
        "symbol": "SNL",
        "chain": "base",
        "price": "$0.0000",
        "amount": "15,000.0000",
        "usdValue": "$0.00"
      }
    ],
    "positions": []
  },
  "analysis": {
    "address": "0x7398944e67dbe99ada77818f120282ab9fe4311c",
    "topProtocols": [
      {
        "name": "LIDO",
        "volume": "$5K"
      },
      {
        "name": "0x6766…2359",
        "volume": "$4K"
      },
      {
        "name": "0x187f…2386",
        "volume": "$2K"
      },
      {
        "name": "0x9740…c35c",
        "volume": "$2K"
      },
      {
        "name": "0x4986…23ad",
        "volume": "$651"
      },
      {
        "name": "0x8216…4fd7",
        "volume": "$594"
      },
      {
        "name": "0xf1f1…2b1b",
        "volume": "$130"
      },
      {
        "name": "0xf0d6…4f4f",
        "volume": "$111"
      },
      {
        "name": "0x9637…ef9a",
        "volume": "$1031"
      },
      {
        "name": "inch",
        "volume": "$69"
      },
      {
        "name": "0x476e…40d2",
        "volume": "$42"
      },
      {
        "name": "0x4045…a5ae",
        "volume": "$41"
      },
      {
        "name": "0xe1fa…b87c",
        "volume": "$40"
      },
      {
        "name": "0xa07d…6a5a",
        "volume": "$unknown"
      },
      {
        "name": "0xdf74…32bb",
        "volume": "$unknown"
      },
      {
        "name": "0x3b5f…b5ee",
        "volume": "$unknown"
      },
      {
        "name": "0x019b…be12",
        "volume": "$unknown"
      },
      {
        "name": "0xcbf4…1fe3",
        "volume": "$unknown"
      }
    ],
    "topTokens": [
      {
        "name": "ETH",
        "volume": "$10K"
      },
      {
        "name": "USDT",
        "volume": "$3K"
      },
      {
        "name": "KNC",
        "volume": "$448"
      },
      {
        "name": "SHIB",
        "volume": "$278"
      },
      {
        "name": "CHZ",
        "volume": "$138"
      },
      {
        "name": "POL",
        "volume": "$40B"
      }
    ]
  },
  "scrapedAt": "2025-12-08T17:21:34.875Z",
  "source": "lido_steth",
  "vaultBalance": 0.36477634158772004,
  "vaultPct": 0.00002739026844167599
}