{
  "portfolio": {
    "address": "0x86b625002ed8391f49f12b67f4e70596fc68eead",
    "totalValue": "$398",
    "walletLifetime": "1435 days",
    "tokens": [
      {
        "symbol": "ETH",
        "chain": "eth",
        "price": "$3,124.9700",
        "amount": "0.1173",
        "usdValue": "$366.49"
      },
      {
        "symbol": "ETH",
        "chain": "arb",
        "price": "$3,124.2700",
        "amount": "0.0101",
        "usdValue": "$31.45"
      }
    ],
    "positions": []
  },
  "analysis": {
    "address": "0x86b625002ed8391f49f12b67f4e70596fc68eead",
    "topProtocols": [
      {
        "name": "StellaSwap",
        "volume": "$36K"
      },
      {
        "name": "SolarFlare",
        "volume": "$16K"
      },
      {
        "name": "Aave V2",
        "volume": "$12K"
      },
      {
        "name": "Uniswap V3",
        "volume": "$10K"
      },
      {
        "name": "SpookySwap",
        "volume": "$9K"
      },
      {
        "name": "The Graph",
        "volume": "$9K"
      },
      {
        "name": "Curve",
        "volume": "$8K"
      },
      {
        "name": "0xf7cd…c5c9",
        "volume": "$6K"
      },
      {
        "name": "0xbcde…745a",
        "volume": "$6K"
      },
      {
        "name": "OpenOcean",
        "volume": "$5K"
      },
      {
        "name": "Arbitrum Bridge",
        "volume": "$4K"
      },
      {
        "name": "Multichain",
        "volume": "$3K"
      },
      {
        "name": "Kraken",
        "volume": "$3K"
      },
      {
        "name": "0xd9b4…922e",
        "volume": "$2K"
      },
      {
        "name": "FTX",
        "volume": "$2K"
      },
      {
        "name": "0x4cbe…56ec",
        "volume": "$2K"
      },
      {
        "name": "Convex",
        "volume": "$1K"
      }
    ],
    "topTokens": [
      {
        "name": "ETH",
        "volume": "$34K"
      },
      {
        "name": "GLMR",
        "volume": "$31K"
      },
      {
        "name": "USDT",
        "volume": "$18K"
      },
      {
        "name": "GRT",
        "volume": "$12K"
      },
      {
        "name": "FTM",
        "volume": "$11K"
      },
      {
        "name": "BNB",
        "volume": "$8K"
      },
      {
        "name": "FLARE",
        "volume": "$7K"
      },
      {
        "name": "STELLA",
        "volume": "$7K"
      },
      {
        "name": "KUSDC",
        "volume": "$6K"
      },
      {
        "name": "KUSDT",
        "volume": "$5K"
      },
      {
        "name": "CRV",
        "volume": "$4K"
      },
      {
        "name": "madUSDC",
        "volume": "$3K"
      },
      {
        "name": "KaxlUSDC",
        "volume": "$3K"
      },
      {
        "name": "cvxCRV",
        "volume": "$3K"
      }
    ]
  },
  "scrapedAt": "2025-12-08T18:27:09.698Z",
  "source": "lido_steth",
  "vaultBalance": 0.32,
  "vaultPct": 0.000024028109562112517
}