{
  "portfolio": {
    "address": "0xa24b8e493ec3388d241f15eab66086bbae0cd89e",
    "totalValue": "$4,998",
    "walletLifetime": "1555 days",
    "tokens": [
      {
        "symbol": "ETH",
        "chain": "scrl",
        "price": "$3,116.0700",
        "amount": "0.2386",
        "usdValue": "$743.39"
      },
      {
        "symbol": "Boop",
        "chain": "arb",
        "price": "$0.0₅9546",
        "amount": "68,148,666.3670",
        "usdValue": "$650.53"
      },
      {
        "symbol": "WETH",
        "chain": "linea",
        "price": "$3,116.0700",
        "amount": "0.1417",
        "usdValue": "$441.67"
      },
      {
        "symbol": "Anon",
        "chain": "sonic",
        "price": "$0.9929",
        "amount": "337.0147",
        "usdValue": "$334.62"
      },
      {
        "symbol": "STONE",
        "chain": "scrl",
        "price": "$3,273.9347",
        "amount": "0.0970",
        "usdValue": "$317.69"
      },
      {
        "symbol": "ETH",
        "chain": "era",
        "price": "$3,116.0700",
        "amount": "0.0962",
        "usdValue": "$299.77"
      },
      {
        "symbol": "ETH",
        "chain": "linea",
        "price": "$3,116.0700",
        "amount": "0.0881",
        "usdValue": "$274.46"
      },
      {
        "symbol": "ETH",
        "chain": "base",
        "price": "$3,116.0700",
        "amount": "0.0746",
        "usdValue": "$232.45"
      },
      {
        "symbol": "ETH",
        "chain": "arb",
        "price": "$3,116.0700",
        "amount": "0.0539",
        "usdValue": "$167.92"
      },
      {
        "symbol": "ZK",
        "chain": "era",
        "price": "$0.0323",
        "amount": "4,000.0000",
        "usdValue": "$129.08"
      },
      {
        "symbol": "ETH",
        "chain": "zora",
        "price": "$3,115.8900",
        "amount": "0.0385",
        "usdValue": "$119.87"
      },
      {
        "symbol": "BITCOIN (HPOS10I)",
        "chain": "eth",
        "price": "$0.0406",
        "amount": "2,571.9600",
        "usdValue": "$104.34"
      },
      {
        "symbol": "pepecoin",
        "chain": "eth",
        "price": "$0.1831",
        "amount": "534.8337",
        "usdValue": "$97.92"
      },
      {
        "symbol": "PEPE",
        "chain": "eth",
        "price": "$0.0₅46",
        "amount": "16,000,158.3200",
        "usdValue": "$73.59"
      },
      {
        "symbol": "imgnAI",
        "chain": "base",
        "price": "$0.0045",
        "amount": "15,000.0000",
        "usdValue": "$67.33"
      },
      {
        "symbol": "HYPE",
        "chain": "hyper",
        "price": "$28.2090",
        "amount": "1.9999",
        "usdValue": "$56.42"
      },
      {
        "symbol": "ETH",
        "chain": "eth",
        "price": "$3,116.0700",
        "amount": "0.0160",
        "usdValue": "$49.96"
      },
      {
        "symbol": "Anon",
        "chain": "hyper",
        "price": "$1.0128",
        "amount": "40.0000",
        "usdValue": "$40.51"
      },
      {
        "symbol": "ETH",
        "chain": "nova",
        "price": "$3,116.0700",
        "amount": "0.0094",
        "usdValue": "$29.26"
      },
      {
        "symbol": "LINEA",
        "chain": "linea",
        "price": "$0.0078",
        "amount": "3,734.3272",
        "usdValue": "$29.20"
      },
      {
        "symbol": "AVAX",
        "chain": "avax",
        "price": "$13.6500",
        "amount": "2.1142",
        "usdValue": "$28.86"
      },
      {
        "symbol": "ZRO",
        "chain": "base",
        "price": "$1.3870",
        "amount": "20.5646",
        "usdValue": "$28.52"
      },
      {
        "symbol": "WAGMI",
        "chain": "era",
        "price": "$0.0024",
        "amount": "11,031.5920",
        "usdValue": "$26.68"
      },
      {
        "symbol": "S",
        "chain": "sonic",
        "price": "$0.0941",
        "amount": "260.4049",
        "usdValue": "$24.50"
      },
      {
        "symbol": "IMGN",
        "chain": "base",
        "price": "$0.0012",
        "amount": "20,000.0000",
        "usdValue": "$24.27"
      },
      {
        "symbol": "PRIME",
        "chain": "eth",
        "price": "$1.2800",
        "amount": "17.3597",
        "usdValue": "$22.22"
      },
      {
        "symbol": "WAGMI",
        "chain": "kava",
        "price": "$0.0024",
        "amount": "9,110.7299",
        "usdValue": "$22.04"
      },
      {
        "symbol": "WAGMI",
        "chain": "sonic",
        "price": "$0.0024",
        "amount": "7,986.5930",
        "usdValue": "$19.32"
      },
      {
        "symbol": "USDt",
        "chain": "kava",
        "price": "$1.0008",
        "amount": "18.7335",
        "usdValue": "$18.75"
      },
      {
        "symbol": "WETH",
        "chain": "kava",
        "price": "$3,101.9283",
        "amount": "0.0056",
        "usdValue": "$17.32"
      },
      {
        "symbol": "BNB",
        "chain": "bsc",
        "price": "$891.4000",
        "amount": "0.0190",
        "usdValue": "$16.91"
      },
      {
        "symbol": "WAGMI",
        "chain": "metis",
        "price": "$0.0024",
        "amount": "5,597.4649",
        "usdValue": "$13.68"
      },
      {
        "symbol": "wS",
        "chain": "sonic",
        "price": "$0.0941",
        "amount": "139.2609",
        "usdValue": "$13.10"
      },
      {
        "symbol": "WETH",
        "chain": "sonic",
        "price": "$3,113.2100",
        "amount": "0.0039",
        "usdValue": "$12.14"
      },
      {
        "symbol": "WETH",
        "chain": "metis",
        "price": "$3,116.0700",
        "amount": "0.0039",
        "usdValue": "$12.02"
      },
      {
        "symbol": "ZORRO",
        "chain": "era",
        "price": "$0.0₅6791",
        "amount": "1,609,794.9361",
        "usdValue": "$10.93"
      },
      {
        "symbol": "STONE",
        "chain": "manta",
        "price": "$3,269.5922",
        "amount": "0.0030",
        "usdValue": "$9.73"
      },
      {
        "symbol": "atUSD",
        "chain": "gravity",
        "price": "$1.1053",
        "amount": "8.4960",
        "usdValue": "$9.39"
      },
      {
        "symbol": "BTC",
        "chain": "merlin",
        "price": "$90,109.3100",
        "amount": "0.0001",
        "usdValue": "$9.01"
      },
      {
        "symbol": "MNT",
        "chain": "mnt",
        "price": "$1.1040",
        "amount": "6.9410",
        "usdValue": "$7.66"
      },
      {
        "symbol": "VITAI",
        "chain": "arb",
        "price": "$0.0004",
        "amount": "15,251.0217",
        "usdValue": "$6.42"
      },
      {
        "symbol": "ETH",
        "chain": "manta",
        "price": "$3,116.0700",
        "amount": "0.0020",
        "usdValue": "$6.08"
      },
      {
        "symbol": "WKAVA",
        "chain": "kava",
        "price": "$0.1034",
        "amount": "51.8367",
        "usdValue": "$5.36"
      },
      {
        "symbol": "WMETIS",
        "chain": "metis",
        "price": "$6.3000",
        "amount": "0.8077",
        "usdValue": "$5.09"
      }
    ],
    "positions": [
      {
        "protocol": "Hyperliquid",
        "chain": "unknown",
        "category": "Staked",
        "label": "Staked",
        "token": "USDC",
        "usdValue": "$320"
      }
    ]
  },
  "analysis": {
    "address": "0xa24b8e493ec3388d241f15eab66086bbae0cd89e",
    "topProtocols": [
      {
        "name": "ZK Nation",
        "volume": "$21K"
      },
      {
        "name": "Binance",
        "volume": "$14K"
      },
      {
        "name": "SyncSwap",
        "volume": "$13K"
      },
      {
        "name": "0x80c6…bcf8",
        "volume": "$13K"
      },
      {
        "name": "0xe4ed…bce8",
        "volume": "$10K"
      },
      {
        "name": "0x5aea…9a91",
        "volume": "$10K"
      },
      {
        "name": "LI.FI",
        "volume": "$9K"
      },
      {
        "name": "cBridge",
        "volume": "$7K"
      },
      {
        "name": "0x0000…0000",
        "volume": "$7K"
      },
      {
        "name": "Wagmi",
        "volume": "$5K"
      },
      {
        "name": "Camelot",
        "volume": "$5K"
      },
      {
        "name": "Pepecoin",
        "volume": "$5K"
      },
      {
        "name": "SushiSwap",
        "volume": "$4K"
      },
      {
        "name": "Uniswap V3",
        "volume": "$4K"
      },
      {
        "name": "0x2ce9…4983",
        "volume": "$3K"
      },
      {
        "name": "Symbiosis",
        "volume": "$3K"
      },
      {
        "name": "0x3613…dc9e",
        "volume": "$3K"
      }
    ],
    "topTokens": [
      {
        "name": "ZK",
        "volume": "$46K"
      },
      {
        "name": "ETH",
        "volume": "$37K"
      },
      {
        "name": "WETH",
        "volume": "$13K"
      },
      {
        "name": "USDC",
        "volume": "$8K"
      },
      {
        "name": "pepecoin",
        "volume": "$6K"
      },
      {
        "name": "WAGMI",
        "volume": "$6K"
      },
      {
        "name": "KBoop",
        "volume": "$5K"
      },
      {
        "name": "AVAX",
        "volume": "$5K"
      },
      {
        "name": "GMX",
        "volume": "$4K"
      },
      {
        "name": "ARB",
        "volume": "$4K"
      },
      {
        "name": "STONE",
        "volume": "$4K"
      },
      {
        "name": "SUSHI",
        "volume": "$3K"
      }
    ]
  },
  "scrapedAt": "2025-12-09T05:43:31.012Z",
  "source": "moonwell",
  "vaultBalance": 0.059996507340437835,
  "vaultPct": 0.001088470217126435
}